{"default":"groupes","root":"ical/2022-2023/q2/","data":{"cours":{"name":"Cours","items":{"AGLR4":{"name":"AGLR4","calendar":"cours/AGLR4.ics"},"AGRI4":{"name":"AGRI4","calendar":"cours/AGRI4.ics"},"AGWR4":{"name":"AGWR4","calendar":"cours/AGWR4.ics"},"ALG2":{"name":"ALG2","calendar":"cours/ALG2.ics"},"ANA2":{"name":"ANA2","calendar":"cours/ANA2.ics"},"ASA":{"name":"ASA","calendar":"cours/ASA.ics"},"ATLG4-atl":{"name":"ATLG4-atl","calendar":"cours/ATLG4-atl.ics"},"ATLIR4":{"name":"ATLIR4","calendar":"cours/ATLIR4.ics"},"ATLIR6-atlc":{"name":"ATLIR6-atlc","calendar":"cours/ATLIR6-atlc.ics"},"ATLIR6-atlj":{"name":"ATLIR6-atlj","calendar":"cours/ATLIR6-atlj.ics"},"AVAI4-phy":{"name":"AVAI4-phy","calendar":"cours/AVAI4-phy.ics"},"AVAI4-van":{"name":"AVAI4-van","calendar":"cours/AVAI4-van.ics"},"CAI2":{"name":"CAI2","calendar":"cours/CAI2.ics"},"CPRG4-cpr":{"name":"CPRG4-cpr","calendar":"cours/CPRG4-cpr.ics"},"CPT1":{"name":"CPT1","calendar":"cours/CPT1.ics"},"CPTG4":{"name":"CPTG4","calendar":"cours/CPTG4.ics"},"CRY":{"name":"CRY","calendar":"cours/CRY.ics"},"DCF":{"name":"DCF","calendar":"cours/DCF.ics"},"DEV2-jav":{"name":"DEV2-jav","calendar":"cours/DEV2-jav.ics"},"DEV2-javl":{"name":"DEV2-javl","calendar":"cours/DEV2-javl.ics"},"DEV4-cppl":{"name":"DEV4-cppl","calendar":"cours/DEV4-cppl.ics"},"DON2-per":{"name":"DON2-per","calendar":"cours/DON2-per.ics"},"DON2-perl":{"name":"DON2-perl","calendar":"cours/DON2-perl.ics"},"DON4":{"name":"DON4","calendar":"cours/DON4.ics"},"DONG6":{"name":"DONG6","calendar":"cours/DONG6.ics"},"DRO":{"name":"DRO","calendar":"cours/DRO.ics"},"ECOG4":{"name":"ECOG4","calendar":"cours/ECOG4.ics"},"EMBI4":{"name":"EMBI4","calendar":"cours/EMBI4.ics"},"ERGG4":{"name":"ERGG4","calendar":"cours/ERGG4.ics"},"IMGI4":{"name":"IMGI4","calendar":"cours/IMGI4.ics"},"IOTI4":{"name":"IOTI4","calendar":"cours/IOTI4.ics"},"LPDG4":{"name":"LPDG4","calendar":"cours/LPDG4.ics"},"MAT1":{"name":"MAT1","calendar":"cours/MAT1.ics"},"MAT1_ou_DEV1":{"name":"MAT1_ou_DEV1","calendar":"cours/MAT1_ou_DEV1.ics"},"MIC2-mic":{"name":"MIC2-mic","calendar":"cours/MIC2-mic.ics"},"MIC2-micl":{"name":"MIC2-micl","calendar":"cours/MIC2-micl.ics"},"MOBG6":{"name":"MOBG6","calendar":"cours/MOBG6.ics"},"PHYIR2-phy":{"name":"PHYIR2-phy","calendar":"cours/PHYIR2-phy.ics"},"PHYIR2-phyl":{"name":"PHYIR2-phyl","calendar":"cours/PHYIR2-phyl.ics"},"RAD":{"name":"RAD","calendar":"cours/RAD.ics"},"RESIR2":{"name":"RESIR2","calendar":"cours/RESIR2.ics"},"RLII4":{"name":"RLII4","calendar":"cours/RLII4.ics"},"SECG4-sec":{"name":"SECG4-sec","calendar":"cours/SECG4-sec.ics"},"STA2":{"name":"STA2","calendar":"cours/STA2.ics"},"SYS2":{"name":"SYS2","calendar":"cours/SYS2.ics"},"SYS4-sysl":{"name":"SYS4-sysl","calendar":"cours/SYS4-sysl.ics"},"SYS4":{"name":"SYS4","calendar":"cours/SYS4.ics"},"SYSG6":{"name":"SYSG6","calendar":"cours/SYSG6.ics"},"TAV":{"name":"TAV","calendar":"cours/TAV.ics"},"TEX":{"name":"TEX","calendar":"cours/TEX.ics"},"WANR4-wan":{"name":"WANR4-wan","calendar":"cours/WANR4-wan.ics"},"WANR4-wanl":{"name":"WANR4-wanl","calendar":"cours/WANR4-wanl.ics"},"WEBG2-web":{"name":"WEBG2-web","calendar":"cours/WEBG2-web.ics"},"WEBG2-webl":{"name":"WEBG2-webl","calendar":"cours/WEBG2-webl.ics"},"WEBG4":{"name":"WEBG4","calendar":"cours/WEBG4.ics"},"WEBG6":{"name":"WEBG6","calendar":"cours/WEBG6.ics"},"WEBR4-din":{"name":"WEBR4-din","calendar":"cours/WEBR4-din.ics"},"WEBR4-xml":{"name":"WEBR4-xml","calendar":"cours/WEBR4-xml.ics"},"WIRR4-rsm":{"name":"WIRR4-rsm","calendar":"cours/WIRR4-rsm.ics"}}},"groupes":{"name":"Groupes","items":{"B111":{"name":"B111","calendar":"groupes/B111.ics"},"B112":{"name":"B112","calendar":"groupes/B112.ics"},"B113":{"name":"B113","calendar":"groupes/B113.ics"},"B121":{"name":"B121","calendar":"groupes/B121.ics"},"B122":{"name":"B122","calendar":"groupes/B122.ics"},"B123":{"name":"B123","calendar":"groupes/B123.ics"},"B131":{"name":"B131","calendar":"groupes/B131.ics"},"B132":{"name":"B132","calendar":"groupes/B132.ics"},"B133":{"name":"B133","calendar":"groupes/B133.ics"},"B141":{"name":"B141","calendar":"groupes/B141.ics"},"B142":{"name":"B142","calendar":"groupes/B142.ics"},"B211":{"name":"B211","calendar":"groupes/B211.ics"},"B212":{"name":"B212","calendar":"groupes/B212.ics"},"B213":{"name":"B213","calendar":"groupes/B213.ics"},"B221":{"name":"B221","calendar":"groupes/B221.ics"},"B222":{"name":"B222","calendar":"groupes/B222.ics"},"B223":{"name":"B223","calendar":"groupes/B223.ics"},"D111":{"name":"D111","calendar":"groupes/D111.ics"},"D112":{"name":"D112","calendar":"groupes/D112.ics"},"D121":{"name":"D121","calendar":"groupes/D121.ics"},"D122":{"name":"D122","calendar":"groupes/D122.ics"},"D211":{"name":"D211","calendar":"groupes/D211.ics"},"D212":{"name":"D212","calendar":"groupes/D212.ics"},"D221":{"name":"D221","calendar":"groupes/D221.ics"},"G1":{"name":"G1","calendar":"groupes/G1.ics"},"G2":{"name":"G2","calendar":"groupes/G2.ics"},"IR1":{"name":"IR1","calendar":"groupes/IR1.ics"},"SEC4A":{"name":"SEC4A","calendar":"groupes/SEC4A.ics"},"SEC4B":{"name":"SEC4B","calendar":"groupes/SEC4B.ics"}}},"profs":{"name":"Profs","items":{"ABS":{"name":"ABS - Romain Absil","calendar":"profs/ABS.ics"},"ARO":{"name":"ARO - Anne Rousseau","calendar":"profs/ARO.ics"},"BEJ":{"name":"BEJ - Jonas Beleho","calendar":"profs/BEJ.ics"},"BIS":{"name":"BIS - Patrick Bischop","calendar":"profs/BIS.ics"},"CLG":{"name":"CLG - Christine Leignel","calendar":"profs/CLG.ics"},"CUV":{"name":"CUV - Geneviève Cuvelier","calendar":"profs/CUV.ics"},"DBO":{"name":"DBO - Denis Boigelot","calendar":"profs/DBO.ics"},"DNA":{"name":"DNA - David Nabet","calendar":"profs/DNA.ics"},"EGR":{"name":"EGR - Éric Georges","calendar":"profs/EGR.ics"},"GBA":{"name":"GBA - Grégory Baltus","calendar":"profs/GBA.ics"},"HAL":{"name":"HAL - Amine Hallal","calendar":"profs/HAL.ics"},"JLC":{"name":"JLC - Jonathan Lechien","calendar":"profs/JLC.ics"},"JSS":{"name":"JSS - Jean-Sébastien Stoffen","calendar":"profs/JSS.ics"},"JST":{"name":"JST - Jovana Stanojevic","calendar":"profs/JST.ics"},"LBC":{"name":"LBC - Laurent Beeckmans","calendar":"profs/LBC.ics"},"LMA":{"name":"LMA - Luis Martinez Sanchez","calendar":"profs/LMA.ics"},"MAP":{"name":"MAP - Michel Applaincourt","calendar":"profs/MAP.ics"},"MBA":{"name":"MBA - Monica Bastreghi","calendar":"profs/MBA.ics"},"MBR":{"name":"MBR - Macelo Burda","calendar":"profs/MBR.ics"},"MHI":{"name":"MHI - Mohamed Hadjili","calendar":"profs/MHI.ics"},"MWA":{"name":"MWA - Moussa Wahid","calendar":"profs/MWA.ics"},"NRI":{"name":"NRI - Nicolas Richard","calendar":"profs/NRI.ics"},"NVS":{"name":"NVS - Nicolas Vansteenkiste","calendar":"profs/NVS.ics"},"PBT":{"name":"PBT - Pierre Bettens","calendar":"profs/PBT.ics"},"PMA":{"name":"PMA - Pantelis Matsos","calendar":"profs/PMA.ics"},"QHB":{"name":"QHB - Quentin Houben","calendar":"profs/QHB.ics"},"RMA":{"name":"RMA - Rudy Mathieu","calendar":"profs/RMA.ics"},"SDR":{"name":"SDR - Sébastien Drobisz","calendar":"profs/SDR.ics"},"SRE":{"name":"SRE - Selim Rexhep","calendar":"profs/SRE.ics"},"SRV":{"name":"SRV - Frédéric Servais","calendar":"profs/SRV.ics"},"TNI":{"name":"TNI - Thibaut Nicodeme","calendar":"profs/TNI.ics"},"TSM":{"name":"TSM - Thierry Simon","calendar":"profs/TSM.ics"},"XPA":{"name":"XPA - Xavier Paulus","calendar":"profs/XPA.ics"},"YVO":{"name":"YVO - Yannick Voglaire","calendar":"profs/YVO.ics"}}},"salles":{"name":"Salles","items":{"101":{"name":"101","calendar":"salles/101.ics"},"102":{"name":"102","calendar":"salles/102.ics"},"105":{"name":"105","calendar":"salles/105.ics"},"202":{"name":"202","calendar":"salles/202.ics"},"203":{"name":"203","calendar":"salles/203.ics"},"204":{"name":"204","calendar":"salles/204.ics"},"301":{"name":"301","calendar":"salles/301.ics"},"303":{"name":"303","calendar":"salles/303.ics"},"304":{"name":"304","calendar":"salles/304.ics"},"305":{"name":"305","calendar":"salles/305.ics"},"401":{"name":"401","calendar":"salles/401.ics"},"403":{"name":"403","calendar":"salles/403.ics"},"404":{"name":"404","calendar":"salles/404.ics"},"405":{"name":"405","calendar":"salles/405.ics"},"502":{"name":"502","calendar":"salles/502.ics"},"503":{"name":"503","calendar":"salles/503.ics"},"504":{"name":"504","calendar":"salles/504.ics"},"505":{"name":"505","calendar":"salles/505.ics"},"601":{"name":"601","calendar":"salles/601.ics"},"602":{"name":"602","calendar":"salles/602.ics"},"604":{"name":"604","calendar":"salles/604.ics"},"003":{"name":"003","calendar":"salles/003.ics"},"004":{"name":"004","calendar":"salles/004.ics"}}}}}
